<?xml version="1.0" encoding="utf-8"?>
<Return xmlns="http://www.irs.gov/efile" xmlns:xsi="http://www.w3.org/2001/XMLSchema-instance" returnVersion="2010v3.2">
  <ReturnHeader binaryAttachmentCount="0">
    <Timestamp>2011-07-27T14:25:54-05:00</Timestamp>
    <TaxPeriodEndDate>2010-12-31</TaxPeriodEndDate>
    <PreparerFirm>
      <PreparerFirmBusinessName>
        <BusinessNameLine1>GUSTAFSON &amp; CO CPA'S</BusinessNameLine1>
      </PreparerFirmBusinessName>
      <PreparerFirmUSAddress>
        <AddressLine1>2249 STATE ROUTE 5</AddressLine1>
        <City>UTICA</City>
        <State>NY</State>
        <ZIPCode>13502</ZIPCode>
      </PreparerFirmUSAddress>
    </PreparerFirm>
    <ReturnType>990EZ</ReturnType>
    <TaxPeriodBeginDate>2010-01-01</TaxPeriodBeginDate>
    <Filer>
      <EIN>300070872</EIN>
      <Name>
        <BusinessNameLine1>HERKIMER CO VOL FIREMENS ASSOC INC</BusinessNameLine1>
      </Name>
      <NameControl>HERK</NameControl>
      <Phone>3157338044</Phone>
      <USAddress>
        <AddressLine1>54 COLUMBIA ST</AddressLine1>
        <City>MOHAWK</City>
        <State>NY</State>
        <ZIPCode>13407</ZIPCode>
      </USAddress>
    </Filer>
    <Officer>
      <Name>JEFF JONES</Name>
      <Title>TREASURER</Title>
      <Phone>3157338044</Phone>
      <DateSigned>2011-06-10</DateSigned>
    </Officer>
    <Preparer>
      <Name>NANCY A BEADLE CPA</Name>
      <Phone>3157350705</Phone>
      <DatePrepared>2011-07-27</DatePrepared>
    </Preparer>
    <TaxYear>2010</TaxYear>
    <BuildTS>2016-02-24 21:20:13Z</BuildTS>
  </ReturnHeader>
  <ReturnData documentCount="3">
    <IRS990EZ documentId="RetDoc3" referenceDocumentId="RetDoc2">
      <MethodOfAccountingCash>X</MethodOfAccountingCash>
      <ScheduleBNotRequired>X</ScheduleBNotRequired>
      <WebSite>N/A</WebSite>
      <Organization501c typeOf501cOrganization="4">X</Organization501c>
      <GrossReceipts>2198</GrossReceipts>
      <InfoInScheduleOPartI>X</InfoInScheduleOPartI>
      <ContributionsGiftsGrantsEtc>1295</ContributionsGiftsGrantsEtc>
      <MembershipDues>864</MembershipDues>
      <InvestmentIncome>39</InvestmentIncome>
      <TotalRevenue>2198</TotalRevenue>
      <FeesAndOthPymtToIndContractors>795</FeesAndOthPymtToIndContractors>
      <OtherExpensesTotal>3376</OtherExpensesTotal>
      <TotalExpenses>4171</TotalExpenses>
      <ExcessOrDeficitForYear>-1973</ExcessOrDeficitForYear>
      <NetAssetsOrFundBalancesBOY>9523</NetAssetsOrFundBalancesBOY>
      <OtherChangesInNetAssets>9161</OtherChangesInNetAssets>
      <NetAssetsOrFundBalancesEOY>16711</NetAssetsOrFundBalancesEOY>
      <InfoInScheduleOPartII>X</InfoInScheduleOPartII>
      <CashSavingsAndInvestments>
        <BOY>9523</BOY>
        <EOY>16456</EOY>
      </CashSavingsAndInvestments>
      <OtherAssetsTotal>
        <EOY>700</EOY>
      </OtherAssetsTotal>
      <TotalAssets>
        <BOY>9523</BOY>
        <EOY>17156</EOY>
      </TotalAssets>
      <SumOfTotalLiabilities>
        <EOY>445</EOY>
      </SumOfTotalLiabilities>
      <NetAssetsOrFundBalances>
        <BOY>9523</BOY>
        <EOY>16711</EOY>
      </NetAssetsOrFundBalances>
      <PrimaryExemptPurpose>FIRE EDUCATION AND COOPERATION AMONG FIRE COMPANIES</PrimaryExemptPurpose>
      <ProgramServiceAccomplishment>
        <DescriptionProgramServiceAccom>THE COMPANY PROMOTES SOCIAL AND MUTUAL UNDERSTANDING OF FIRE DEPARTMENTS BY FURTHERING EDUCATION, PROMOTE LEGISLATION, TO COOPERATE WITH OTHER FIRE ASSOCIATIONS.</DescriptionProgramServiceAccom>
        <ProgramServiceExpenses>1390</ProgramServiceExpenses>
      </ProgramServiceAccomplishment>
      <TotalProgramServiceExpenses>1390</TotalProgramServiceExpenses>
      <OfficerDirectorTrusteeKeyEmpl>
        <PersonName referenceDocumentId="RetDoc1">DAVE SPENCER</PersonName>
        <AddressUS>
          <AddressLine1>54 COLUMBIA STREET</AddressLine1>
          <City>MOHAWK</City>
          <State>NY</State>
          <ZIPCode>13407</ZIPCode>
        </AddressUS>
        <Title>PRESIDENT</Title>
        <AvgHoursPerWkDevotedToPosition>1.00</AvgHoursPerWkDevotedToPosition>
        <Compensation>0</Compensation>
      </OfficerDirectorTrusteeKeyEmpl>
      <OfficerDirectorTrusteeKeyEmpl>
        <PersonName referenceDocumentId="RetDoc1">SENAN GREENE</PersonName>
        <AddressUS>
          <AddressLine1>54 COLUMBIA ST</AddressLine1>
          <City>MOHAWK</City>
          <State>NY</State>
          <ZIPCode>13407</ZIPCode>
        </AddressUS>
        <Title>1ST VICE PRE</Title>
        <AvgHoursPerWkDevotedToPosition>1.00</AvgHoursPerWkDevotedToPosition>
        <Compensation>0</Compensation>
      </OfficerDirectorTrusteeKeyEmpl>
      <OfficerDirectorTrusteeKeyEmpl>
        <PersonName referenceDocumentId="RetDoc1">FRED GRIFFIN</PersonName>
        <AddressUS>
          <AddressLine1>54 COLUMBIA ST</AddressLine1>
          <City>MOHAWK</City>
          <State>NY</State>
          <ZIPCode>13407</ZIPCode>
        </AddressUS>
        <Title>2ND VICE PRE</Title>
        <AvgHoursPerWkDevotedToPosition>1.00</AvgHoursPerWkDevotedToPosition>
        <Compensation>0</Compensation>
      </OfficerDirectorTrusteeKeyEmpl>
      <OfficerDirectorTrusteeKeyEmpl>
        <PersonName referenceDocumentId="RetDoc1">RICK SUSKIE</PersonName>
        <AddressUS>
          <AddressLine1>54 COLUMBIA ST</AddressLine1>
          <City>MOHAWK</City>
          <State>NY</State>
          <ZIPCode>13407</ZIPCode>
        </AddressUS>
        <Title>3RD VICE PRE</Title>
        <AvgHoursPerWkDevotedToPosition>1.00</AvgHoursPerWkDevotedToPosition>
        <Compensation>0</Compensation>
      </OfficerDirectorTrusteeKeyEmpl>
      <OfficerDirectorTrusteeKeyEmpl>
        <PersonName referenceDocumentId="RetDoc1">THOMAS MARIANO</PersonName>
        <AddressUS>
          <AddressLine1>54 COLUMBIA ST</AddressLine1>
          <City>MOHAWK</City>
          <State>NY</State>
          <ZIPCode>13407</ZIPCode>
        </AddressUS>
        <Title>4TH VICE PRE</Title>
        <AvgHoursPerWkDevotedToPosition>1.00</AvgHoursPerWkDevotedToPosition>
        <Compensation>0</Compensation>
      </OfficerDirectorTrusteeKeyEmpl>
      <OfficerDirectorTrusteeKeyEmpl>
        <PersonName referenceDocumentId="RetDoc1">DON ELTHORP</PersonName>
        <AddressUS>
          <AddressLine1>54 COLUMBIA ST</AddressLine1>
          <City>MOHAWK</City>
          <State>NY</State>
          <ZIPCode>13407</ZIPCode>
        </AddressUS>
        <Title>CHAPLAIN</Title>
        <AvgHoursPerWkDevotedToPosition>1.00</AvgHoursPerWkDevotedToPosition>
        <Compensation>0</Compensation>
      </OfficerDirectorTrusteeKeyEmpl>
      <OfficerDirectorTrusteeKeyEmpl>
        <PersonName referenceDocumentId="RetDoc1">LARRY SICKLER</PersonName>
        <AddressUS>
          <AddressLine1>54 COLUMBIA ST</AddressLine1>
          <City>MOHAWK</City>
          <State>NY</State>
          <ZIPCode>13407</ZIPCode>
        </AddressUS>
        <Title>SECRETARY</Title>
        <AvgHoursPerWkDevotedToPosition>1.00</AvgHoursPerWkDevotedToPosition>
        <Compensation>100</Compensation>
      </OfficerDirectorTrusteeKeyEmpl>
      <OfficerDirectorTrusteeKeyEmpl>
        <PersonName referenceDocumentId="RetDoc1">JEFF JONES</PersonName>
        <AddressUS>
          <AddressLine1>54 COLUMBIA ST</AddressLine1>
          <City>MOHAWK</City>
          <State>NY</State>
          <ZIPCode>13407</ZIPCode>
        </AddressUS>
        <Title>TREASURER</Title>
        <AvgHoursPerWkDevotedToPosition>1.00</AvgHoursPerWkDevotedToPosition>
        <Compensation>100</Compensation>
      </OfficerDirectorTrusteeKeyEmpl>
      <OfficerDirectorTrusteeKeyEmpl>
        <PersonName referenceDocumentId="RetDoc1">JASON COOK</PersonName>
        <AddressUS>
          <AddressLine1>54 COLUMBIA ST</AddressLine1>
          <City>MOHAWK</City>
          <State>NY</State>
          <ZIPCode>13407</ZIPCode>
        </AddressUS>
        <Title>SGT AT ARMS</Title>
        <AvgHoursPerWkDevotedToPosition>1.00</AvgHoursPerWkDevotedToPosition>
        <Compensation>0</Compensation>
      </OfficerDirectorTrusteeKeyEmpl>
      <ActivitiesNotPreviouslyRpt>false</ActivitiesNotPreviouslyRpt>
      <MadeChangesToOrgnzngEtcDoc>false</MadeChangesToOrgnzngEtcDoc>
      <OrganizationHadUBI>false</OrganizationHadUBI>
      <OrganizationDissolvedEtc>false</OrganizationDissolvedEtc>
      <DidOrgFileForm1120POLThisYear>false</DidOrgFileForm1120POLThisYear>
      <MadeLoansToFromOfficers>false</MadeLoansToFromOfficers>
      <EngagedInExcessBenefitTrans>false</EngagedInExcessBenefitTrans>
      <ProhibitedTaxShelterTrans>false</ProhibitedTaxShelterTrans>
      <StatesWhereCopyOfReturnIsFiled>NY</StatesWhereCopyOfReturnIsFiled>
      <TheBooksAreInCareOf>
        <NamePerson>JEFF JONES</NamePerson>
        <AddressUS>
          <AddressLine1>4411 STATE ROUTE 5</AddressLine1>
          <City>FRANKFORT</City>
          <State>NY</State>
          <ZIPCode>13340</ZIPCode>
        </AddressUS>
        <TelephoneNumber>3153606401</TelephoneNumber>
      </TheBooksAreInCareOf>
      <ForeignFinancialAccount>false</ForeignFinancialAccount>
      <ForeignOffice>false</ForeignOffice>
      <MaintainAnyDonorAdvisedFunds>false</MaintainAnyDonorAdvisedFunds>
      <DoesOrgHaveHospital>false</DoesOrgHaveHospital>
      <TanningServicesProvided>false</TanningServicesProvided>
      <RelatedOrgControlledEntity>false</RelatedOrgControlledEntity>
      <TransactionWithControlEntity>false</TransactionWithControlEntity>
      <EngagePoliticalCmpgnActivities>false</EngagePoliticalCmpgnActivities>
    </IRS990EZ>
    <IRS990ScheduleO documentId="RetDoc2">
      <GeneralExplanation>
        <Identifier>OTHER EXPENSES</Identifier>
        <ReturnReference>FORM 990-EZ, PART I, LINE 16</ReturnReference>
        <Explanation>EXPENSES ADVERTISING -100 OFFICE EXPENSE 186 CONVENTIONS/BANQUETS 40 CONFERENCES 1,100 INSURANCE 971 DUES 100 GIFTS 100 RAFFLE EXPENSE 929 DONATIONS 50 TOTAL 3,376</Explanation>
      </GeneralExplanation>
      <GeneralExplanation>
        <Identifier>OTHER CHANGES IN NET ASSETS OR FUND BALANCES</Identifier>
        <ReturnReference>FORM 990-EZ, PART I, LINE 20</ReturnReference>
        <Explanation>PRIOR YEAR ADJUSTMENT 9,161</Explanation>
      </GeneralExplanation>
      <GeneralExplanation>
        <Identifier>OTHER ASSETS</Identifier>
        <ReturnReference>FORM 990-EZ, PART II, LINE 24</ReturnReference>
        <Explanation>ACCOUNTS RECEIVABLE 0 700 TOTAL 0 700</Explanation>
      </GeneralExplanation>
      <GeneralExplanation>
        <Identifier>OTHER LIABILITIES</Identifier>
        <ReturnReference>FORM 990-EZ, PART II, LINE 26</ReturnReference>
        <Explanation>ACCOUNTS PAYABLE AND ACCRUED EXPENSES 0 445</Explanation>
      </GeneralExplanation>
    </IRS990ScheduleO>
    <CompensationExplanation documentId="RetDoc1">
      <Compensation>
        <PersonName>DAVE SPENCER</PersonName>
      </Compensation>
      <Compensation>
        <PersonName>SENAN GREENE</PersonName>
      </Compensation>
      <Compensation>
        <PersonName>FRED GRIFFIN</PersonName>
      </Compensation>
      <Compensation>
        <PersonName>RICK SUSKIE</PersonName>
      </Compensation>
      <Compensation>
        <PersonName>THOMAS MARIANO</PersonName>
      </Compensation>
      <Compensation>
        <PersonName>DON ELTHORP</PersonName>
      </Compensation>
      <Compensation>
        <PersonName>LARRY SICKLER</PersonName>
      </Compensation>
      <Compensation>
        <PersonName>JEFF JONES</PersonName>
      </Compensation>
      <Compensation>
        <PersonName>JASON COOK</PersonName>
      </Compensation>
    </CompensationExplanation>
  </ReturnData>
</Return>