<?xml version="1.0" encoding="utf-8"?>
<Return xmlns="http://www.irs.gov/efile" returnVersion="2010v3.4">
  <ReturnHeader binaryAttachmentCount="0">
    <Timestamp>2011-07-28T18:31:42-05:00</Timestamp>
    <TaxPeriodEndDate>2011-06-30</TaxPeriodEndDate>
    <PreparerFirm>
      <PreparerFirmBusinessName>
        <BusinessNameLine1>Regina R Young CPA</BusinessNameLine1>
      </PreparerFirmBusinessName>
      <PreparerFirmUSAddress>
        <AddressLine1>501 E Maple Street</AddressLine1>
        <City>Fayetteville</City>
        <State>AR</State>
        <ZIPCode>72701</ZIPCode>
      </PreparerFirmUSAddress>
    </PreparerFirm>
    <ReturnType>990</ReturnType>
    <TaxPeriodBeginDate>2010-07-01</TaxPeriodBeginDate>
    <Filer>
      <EIN>710673722</EIN>
      <Name>
        <BusinessNameLine1>KAPPA DELTA SORORITY ZETA GAMMA</BusinessNameLine1>
      </Name>
      <NameControl>KAPP</NameControl>
      <USAddress>
        <AddressLine1>404 WEST MAPLE STREET</AddressLine1>
        <City>FAYETTEVILLE</City>
        <State>AR</State>
        <ZIPCode>72701</ZIPCode>
      </USAddress>
    </Filer>
    <Officer>
      <Name>Christy Sams</Name>
      <Title>Chairman</Title>
      <Phone>4794448820</Phone>
      <DateSigned>2011-07-27</DateSigned>
      <AuthorizeThirdParty>false</AuthorizeThirdParty>
    </Officer>
    <Preparer>
      <Name>Regina R Young CPA</Name>
      <Phone>4794448820</Phone>
      <DatePrepared>2011-07-28</DatePrepared>
    </Preparer>
    <TaxYear>2010</TaxYear>
    <BuildTS>2016-02-24 21:20:13Z</BuildTS>
  </ReturnHeader>
  <ReturnData documentCount="6">
    <IRS990 documentId="990">
      <NameOfPrincipalOfficerPerson>Shannon Grise</NameOfPrincipalOfficerPerson>
      <AddressPrincipalOfficerUS>
        <AddressLine1>404 W Maple</AddressLine1>
        <City>Fayetteville</City>
        <State>AR</State>
        <ZIPCode>72701</ZIPCode>
      </AddressPrincipalOfficerUS>
      <GrossReceipts>268599</GrossReceipts>
      <GroupReturnForAffiliates>false</GroupReturnForAffiliates>
      <Organization501c typeOf501cOrganization="7">X</Organization501c>
      <TypeOfOrganizationCorporation>X</TypeOfOrganizationCorporation>
      <YearFormation>1989</YearFormation>
      <StateLegalDomicile>AR</StateLegalDomicile>
      <ActivityOrMissionDescription>University Sorority</ActivityOrMissionDescription>
      <NbrVotingMembersGoverningBody>0</NbrVotingMembersGoverningBody>
      <NbrIndependentVotingMembers>0</NbrIndependentVotingMembers>
      <TotalNbrEmployees>0</TotalNbrEmployees>
      <TotalGrossUBI>0</TotalGrossUBI>
      <NetUnrelatedBusinessTxblIncome>0</NetUnrelatedBusinessTxblIncome>
      <ContributionsGrantsPriorYear>263771</ContributionsGrantsPriorYear>
      <ContributionsGrantsCurrentYear>268599</ContributionsGrantsCurrentYear>
      <ProgramServiceRevenueCY>0</ProgramServiceRevenueCY>
      <InvestmentIncomeCurrentYear>0</InvestmentIncomeCurrentYear>
      <OtherRevenueCurrentYear>0</OtherRevenueCurrentYear>
      <TotalRevenuePriorYear>263771</TotalRevenuePriorYear>
      <TotalRevenueCurrentYear>268599</TotalRevenueCurrentYear>
      <GrantsAndSimilarAmntsCY>0</GrantsAndSimilarAmntsCY>
      <BenefitsPaidToMembersCY>0</BenefitsPaidToMembersCY>
      <SalariesEtcCurrentYear>0</SalariesEtcCurrentYear>
      <TotalProfFundrsngExpCY>0</TotalProfFundrsngExpCY>
      <TotalFundrsngExpCurrentYear>0</TotalFundrsngExpCurrentYear>
      <OtherExpensePriorYear>213752</OtherExpensePriorYear>
      <OtherExpensesCurrentYear>267168</OtherExpensesCurrentYear>
      <TotalExpensesPriorYear>213752</TotalExpensesPriorYear>
      <TotalExpensesCurrentYear>267168</TotalExpensesCurrentYear>
      <RevenuesLessExpensesPriorYear>50019</RevenuesLessExpensesPriorYear>
      <RevenuesLessExpensesCY>1431</RevenuesLessExpensesCY>
      <TotalAssetsBOY>73804</TotalAssetsBOY>
      <TotalAssetsEOY>75235</TotalAssetsEOY>
      <TotalLiabilitiesEOY>0</TotalLiabilitiesEOY>
      <NetAssetsOrFundBalancesBOY>73804</NetAssetsOrFundBalancesBOY>
      <NetAssetsOrFundBalancesEOY>75235</NetAssetsOrFundBalancesEOY>
      <MissionDescription>University Sorority</MissionDescription>
      <SignificantNewProgramServices>false</SignificantNewProgramServices>
      <SignificantChange>false</SignificantChange>
      <Expense>267168</Expense>
      <Description>The chapter maintains a meeting place for members of the sorority at the University of Arkansas The chapter uses dues to promote the development of the members through its dedication to philinthropic projects</Description>
      <TotalProgramServiceExpense>267168</TotalProgramServiceExpense>
      <DescribedIn501C3>false</DescribedIn501C3>
      <ScheduleBRequired referenceDocumentId="990B">true</ScheduleBRequired>
      <PoliticalActivities>false</PoliticalActivities>
      <DonorAdvisedFunds>false</DonorAdvisedFunds>
      <ConservationEasements>false</ConservationEasements>
      <CollectionsOfArt>false</CollectionsOfArt>
      <CreditCounseling>false</CreditCounseling>
      <TermOrPermanentEndowments>false</TermOrPermanentEndowments>
      <ReportLandBldgEquip referenceDocumentId="990D">true</ReportLandBldgEquip>
      <ReportInvestOthSecurities>false</ReportInvestOthSecurities>
      <ReportProgRelInvest>false</ReportProgRelInvest>
      <ReportOtherAssets>false</ReportOtherAssets>
      <ReportOtherLiabilities>false</ReportOtherLiabilities>
      <ReportFin48Footnote>false</ReportFin48Footnote>
      <IndependentAuditFinancialStmt>false</IndependentAuditFinancialStmt>
      <ConsolidatedAuditFinancialStmt>false</ConsolidatedAuditFinancialStmt>
      <School>false</School>
      <ForeignOffice>false</ForeignOffice>
      <ForeignActivities>false</ForeignActivities>
      <MoreThan5000KToOrganizations>false</MoreThan5000KToOrganizations>
      <MoreThan5000KToIndividuals>false</MoreThan5000KToIndividuals>
      <ProfessionalFundraising>false</ProfessionalFundraising>
      <FundraisingActivities>false</FundraisingActivities>
      <Gaming>false</Gaming>
      <Hospital>false</Hospital>
      <GrantsToOrganizations>false</GrantsToOrganizations>
      <GrantsToIndividuals>false</GrantsToIndividuals>
      <ScheduleJRequired>false</ScheduleJRequired>
      <TaxExemptBonds>false</TaxExemptBonds>
      <LoanToOfficerOrDQP>false</LoanToOfficerOrDQP>
      <GrantToRelatedPerson>false</GrantToRelatedPerson>
      <BsnssRltnshpWithOrganization>false</BsnssRltnshpWithOrganization>
      <BsnssRltnshpThruFamilyMember>false</BsnssRltnshpThruFamilyMember>
      <OfficerEntityWithBsnssRltnshp>false</OfficerEntityWithBsnssRltnshp>
      <DeductibleNonCashContributions>false</DeductibleNonCashContributions>
      <DeductibleContributionsOfArt>false</DeductibleContributionsOfArt>
      <Terminated>false</Terminated>
      <PartialLiquidation>false</PartialLiquidation>
      <DisregardedEntity>false</DisregardedEntity>
      <RelatedEntity>false</RelatedEntity>
      <RelatedOrgControlledEntity>false</RelatedOrgControlledEntity>
      <TransactionRelatedEntity>false</TransactionRelatedEntity>
      <ActivitiesConductedPartnership>false</ActivitiesConductedPartnership>
      <ScheduleORequired>true</ScheduleORequired>
      <NumberFormsTransmittedWith1096>0</NumberFormsTransmittedWith1096>
      <NumberW2GIncluded>0</NumberW2GIncluded>
      <ComplianceWithBackupWitholding>true</ComplianceWithBackupWitholding>
      <NumberOfEmployees>0</NumberOfEmployees>
      <EmploymentTaxReturnsFiled>false</EmploymentTaxReturnsFiled>
      <UnrelatedBusinessIncome>false</UnrelatedBusinessIncome>
      <ForeignFinancialAccount>false</ForeignFinancialAccount>
      <ProhibitedTaxShelterTrans>false</ProhibitedTaxShelterTrans>
      <TaxablePartyNotification>false</TaxablePartyNotification>
      <NonDeductibleContributions>true</NonDeductibleContributions>
      <NonDeductibleDisclosure>false</NonDeductibleDisclosure>
      <QuidProQuoContributions>false</QuidProQuoContributions>
      <Form8282PropertyDisposedOf>false</Form8282PropertyDisposedOf>
      <FundsToPayPremiums>false</FundsToPayPremiums>
      <PremiumsPaid>false</PremiumsPaid>
      <Form8899Filed>false</Form8899Filed>
      <Form1098CFiled>false</Form1098CFiled>
      <ExcessBusinessHoldings>false</ExcessBusinessHoldings>
      <TaxableDistributions>false</TaxableDistributions>
      <DistributionToDonor>false</DistributionToDonor>
      <InitiationFeesAmount>17325</InitiationFeesAmount>
      <GrossReceiptsAmount>0</GrossReceiptsAmount>
      <IndoorTanningServices>false</IndoorTanningServices>
      <InfoInScheduleOPartVI>X</InfoInScheduleOPartVI>
      <NbrVotingGoverningBodyMembers>0</NbrVotingGoverningBodyMembers>
      <NumberIndependentVotingMembers>0</NumberIndependentVotingMembers>
      <FamilyOrBusinessRelationship>false</FamilyOrBusinessRelationship>
      <DelegationOfManagementDuties>false</DelegationOfManagementDuties>
      <ChangesToOrganizingDocs>false</ChangesToOrganizingDocs>
      <MaterialDiversionOrMisuse>false</MaterialDiversionOrMisuse>
      <MembersOrStockholders>false</MembersOrStockholders>
      <ElectionOfBoardMembers>false</ElectionOfBoardMembers>
      <DecisionsSubjectToApproval>false</DecisionsSubjectToApproval>
      <MinutesOfGoverningBody>true</MinutesOfGoverningBody>
      <MinutesOfCommittees>true</MinutesOfCommittees>
      <OfficerMailingAddress>false</OfficerMailingAddress>
      <LocalChapters>true</LocalChapters>
      <PoliciesReferenceChapters>true</PoliciesReferenceChapters>
      <Form990ProvidedToGoverningBody>false</Form990ProvidedToGoverningBody>
      <ConflictOfInterestPolicy>false</ConflictOfInterestPolicy>
      <WhistleblowerPolicy>false</WhistleblowerPolicy>
      <DocumentRetentionPolicy>false</DocumentRetentionPolicy>
      <CompensationProcessCEO>false</CompensationProcessCEO>
      <CompensationProcessOther>false</CompensationProcessOther>
      <InvestmentInJointVenture>false</InvestmentInJointVenture>
      <WrittenPolicyOrProcedure>false</WrittenPolicyOrProcedure>
      <StatesWhereCopyOfReturnIsFiled>AR</StatesWhereCopyOfReturnIsFiled>
      <UponRequest>X</UponRequest>
      <TheBooksAreInCareOf>
        <NamePerson>Chapter Treasurer</NamePerson>
        <TelephoneNumber>4795216512</TelephoneNumber>
        <AddressUS>
          <AddressLine1>404 W Maple St</AddressLine1>
          <City>Fayetteville</City>
          <State>AR</State>
          <ZIPCode>72701</ZIPCode>
        </AddressUS>
      </TheBooksAreInCareOf>
      <NoListedPersonsCompensated>X</NoListedPersonsCompensated>
      <Form990PartVIISectionA>
        <NamePerson>Christy Sams</NamePerson>
        <Title>CHAIRMAN</Title>
        <AverageHoursPerWeek>2.00</AverageHoursPerWeek>
        <Officer>X</Officer>
        <ReportableCompFromOrganization>0</ReportableCompFromOrganization>
        <ReportableCompFromRelatedOrgs>0</ReportableCompFromRelatedOrgs>
        <OtherCompensation>0</OtherCompensation>
      </Form990PartVIISectionA>
      <Form990PartVIISectionA>
        <NamePerson>Shannon Grise</NamePerson>
        <Title>FINANCE</Title>
        <AverageHoursPerWeek>2.00</AverageHoursPerWeek>
        <Officer>X</Officer>
        <ReportableCompFromOrganization>0</ReportableCompFromOrganization>
        <ReportableCompFromRelatedOrgs>0</ReportableCompFromRelatedOrgs>
        <OtherCompensation>0</OtherCompensation>
      </Form990PartVIISectionA>
      <TotalReportableCompFromOrg>0</TotalReportableCompFromOrg>
      <TotalReportableCompFrmRltdOrgs>0</TotalReportableCompFrmRltdOrgs>
      <TotalOtherCompensation>0</TotalOtherCompensation>
      <NumberIndividualsGT100K>0</NumberIndividualsGT100K>
      <FormersListed>false</FormersListed>
      <TotalCompGT150K>false</TotalCompGT150K>
      <CompensationFromOtherSources>false</CompensationFromOtherSources>
      <MembershipDues>256001</MembershipDues>
      <FundraisingEvents>12598</FundraisingEvents>
      <TotalContributions>268599</TotalContributions>
      <CntrbtnsRprtdFundraisingEvents>12598</CntrbtnsRprtdFundraisingEvents>
      <TotalRevenue>
        <TotalRevenueColumn>268599</TotalRevenueColumn>
        <RelatedOrExemptFunctionIncome>0</RelatedOrExemptFunctionIncome>
        <UnrelatedBusinessRevenue>0</UnrelatedBusinessRevenue>
        <ExclusionAmount>0</ExclusionAmount>
      </TotalRevenue>
      <FeesForServicesAccounting>
        <Total>4500</Total>
        <ProgramServices>4500</ProgramServices>
      </FeesForServicesAccounting>
      <Advertising>
        <Total>2348</Total>
        <ProgramServices>2348</ProgramServices>
      </Advertising>
      <OfficeExpenses>
        <Total>7181</Total>
        <ProgramServices>7181</ProgramServices>
      </OfficeExpenses>
      <OtherExpenses>
        <Description>Omega and Bank Fees</Description>
        <Total>17072</Total>
        <ProgramServices>17072</ProgramServices>
      </OtherExpenses>
      <OtherExpenses>
        <Description>Dev and Philanthrophies</Description>
        <Total>196340</Total>
        <ProgramServices>196340</ProgramServices>
      </OtherExpenses>
      <OtherExpenses>
        <Description>Social Expenses</Description>
        <Total>36527</Total>
        <ProgramServices>36527</ProgramServices>
      </OtherExpenses>
      <OtherExpenses>
        <Description>Self Storage</Description>
        <Total>1886</Total>
        <ProgramServices>1886</ProgramServices>
      </OtherExpenses>
      <OtherExpenses>
        <Description>Miscellaneous</Description>
        <Total>1314</Total>
        <ProgramServices>1314</ProgramServices>
      </OtherExpenses>
      <TotalFunctionalExpenses>
        <Total>267168</Total>
        <ProgramServices>267168</ProgramServices>
        <ManagementAndGeneral>0</ManagementAndGeneral>
        <Fundraising>0</Fundraising>
      </TotalFunctionalExpenses>
      <CashNonInterestBearing>
        <BOY>55347</BOY>
        <EOY>63173</EOY>
      </CashNonInterestBearing>
      <AccountsReceivable>
        <BOY>18457</BOY>
        <EOY>12062</EOY>
      </AccountsReceivable>
      <LandBuildingsEquipmentBasis>14776</LandBuildingsEquipmentBasis>
      <LandBldgEquipmentAccumDeprec>14776</LandBldgEquipmentAccumDeprec>
      <TotalAssets>
        <BOY>73804</BOY>
        <EOY>75235</EOY>
      </TotalAssets>
      <TotalLiabilities>
        <BOY>0</BOY>
        <EOY>0</EOY>
      </TotalLiabilities>
      <FollowSFAS117>X</FollowSFAS117>
      <UnrestrictedNetAssets>
        <BOY>73804</BOY>
        <EOY>75235</EOY>
      </UnrestrictedNetAssets>
      <TotalNetAssetsFundBalances>
        <BOY>73804</BOY>
        <EOY>75235</EOY>
      </TotalNetAssetsFundBalances>
      <TotalLiabNetAssetsFundBalances>
        <BOY>73804</BOY>
        <EOY>75235</EOY>
      </TotalLiabNetAssetsFundBalances>
      <ReconcilationRevenueExpenses>1431</ReconcilationRevenueExpenses>
      <ReconcilationOtherChanges>0</ReconcilationOtherChanges>
      <MethodOfAccountingAccrual>X</MethodOfAccountingAccrual>
      <AccountantCompileOrReview>true</AccountantCompileOrReview>
      <FSAudited>false</FSAudited>
      <AuditCommittee>true</AuditCommittee>
      <FederalGrantAuditRequired>false</FederalGrantAuditRequired>
    </IRS990>
    <IRS990ScheduleA documentId="990A">
      <CollegeSupportOrg170b1Aiv>X</CollegeSupportOrg170b1Aiv>
      <GiftsGrantsContribReceived170>
        <CurrentTaxYearMinus4Years>170597</CurrentTaxYearMinus4Years>
        <CurrentTaxYearMinus3Years>205838</CurrentTaxYearMinus3Years>
        <CurrentTaxYearMinus2Years>222785</CurrentTaxYearMinus2Years>
        <CurrentTaxYearMinus1Year>263771</CurrentTaxYearMinus1Year>
        <CurrentTaxYear>268599</CurrentTaxYear>
        <Total>1131590</Total>
      </GiftsGrantsContribReceived170>
      <Total170>
        <CurrentTaxYearMinus4Years>170597</CurrentTaxYearMinus4Years>
        <CurrentTaxYearMinus3Years>205838</CurrentTaxYearMinus3Years>
        <CurrentTaxYearMinus2Years>222785</CurrentTaxYearMinus2Years>
        <CurrentTaxYearMinus1Year>263771</CurrentTaxYearMinus1Year>
        <CurrentTaxYear>268599</CurrentTaxYear>
        <Total>1131590</Total>
      </Total170>
      <PublicSupportTotal170>1131590</PublicSupportTotal170>
      <TotalSupport>1131590</TotalSupport>
      <PublicSupportPertcentage170>1.00000</PublicSupportPertcentage170>
      <PublicSupportPertcentPriorYear>1.00000</PublicSupportPertcentPriorYear>
      <ThirtyThreePercntTestsCY170>X</ThirtyThreePercntTestsCY170>
    </IRS990ScheduleA>
    <IRS990ScheduleB documentId="990B">
      <ContributorInfo>
        <ContributorNumber>RESTRICTED</ContributorNumber>
        <ContributorNameBusiness>
          <BusinessNameLine1>RESTRICTED</BusinessNameLine1>
        </ContributorNameBusiness>
        <ContributorAddressUS>
          <AddressLine1>RESTRICTED</AddressLine1>
          <AddressLine2>RESTRICTED</AddressLine2>
          <City>RESTRICTED</City>
          <State>RESTRICTED</State>
          <ZIPCode>RESTRICTED</ZIPCode>
        </ContributorAddressUS>
        <AggregateContributions>RESTRICTED</AggregateContributions>
      </ContributorInfo>
    </IRS990ScheduleB>
    <IRS990ScheduleC documentId="990C"></IRS990ScheduleC>
    <IRS990ScheduleD documentId="990D">
      <Equipment>
        <InvestmentCostOrOtherBasis>14776</InvestmentCostOrOtherBasis>
        <Depreciation>14776</Depreciation>
      </Equipment>
    </IRS990ScheduleD>
    <IRS990ScheduleO documentId="990O">
      <GeneralExplanation>
        <Identifier>01. Form 990 governing body review (Part VI, line 11)</Identifier>
        <Explanation>The tax return and monthy compiled financial statements are given to the governing body to review prior to being filed</Explanation>
      </GeneralExplanation>
      <GeneralExplanation>
        <Identifier>02. Governing documents, etc, available to public (Part VI, line 19)</Identifier>
        <Explanation>Documents are made available to the pubic upon request of the individual</Explanation>
      </GeneralExplanation>
    </IRS990ScheduleO>
  </ReturnData>
</Return>